GoodUSB/goodUSB.py
GoodUSB-1.1.dist-info/LICENSE
GoodUSB-1.1.dist-info/METADATA
GoodUSB-1.1.dist-info/WHEEL
GoodUSB-1.1.dist-info/top_level.txt
GoodUSB-1.1.dist-info/RECORD
