Metadata-Version: 2.1
Name: GoodUSB
Version: 1.1
Summary: Prevent BadUSB attacks
Home-page: https://github.com/TINYT1ME/GoodUSB
Author: TINYT1ME
License: MIT
Platform: UNKNOWN
Requires-Dist: pythoncom
Requires-Dist: keyboard
